MANIFEST.in
README.txt
heddex.tranquility-configure.zcml
setup.cfg
setup.py
docs/HISTORY.txt
docs/INSTALL.txt
docs/LICENSE.GPL
docs/LICENSE.txt
heddex/__init__.py
heddex.tranquility.egg-info/PKG-INFO
heddex.tranquility.egg-info/SOURCES.txt
heddex.tranquility.egg-info/dependency_links.txt
heddex.tranquility.egg-info/entry_points.txt
heddex.tranquility.egg-info/namespace_packages.txt
heddex.tranquility.egg-info/not-zip-safe
heddex.tranquility.egg-info/paster_plugins.txt
heddex.tranquility.egg-info/requires.txt
heddex.tranquility.egg-info/top_level.txt
heddex/tranquility/__init__.py
heddex/tranquility/configure.zcml
heddex/tranquility/profiles.zcml
heddex/tranquility/setuphandlers.py
heddex/tranquility/skins.zcml
heddex/tranquility/tests.py
heddex/tranquility/version.txt
heddex/tranquility/browser/__init__.py
heddex/tranquility/browser/common.py
heddex/tranquility/browser/configure.zcml
heddex/tranquility/browser/interfaces.py
heddex/tranquility/browser/path_bar.pt
heddex/tranquility/browser/sections.pt
heddex/tranquility/browser/images/README.txt
heddex/tranquility/browser/stylesheets/README.txt
heddex/tranquility/browser/stylesheets/main.css
heddex/tranquility/portlets/__init__.py
heddex/tranquility/portlets/configure.zcml
heddex/tranquility/portlets/personaltools.pt
heddex/tranquility/portlets/personaltools.py
heddex/tranquility/profiles/default/cssregistry.xml
heddex/tranquility/profiles/default/heddex.tranquility_various.txt
heddex/tranquility/profiles/default/import_steps.xml
heddex/tranquility/profiles/default/jsregistry.xml
heddex/tranquility/profiles/default/metadata.xml
heddex/tranquility/profiles/default/portlets.xml
heddex/tranquility/profiles/default/skins.xml
heddex/tranquility/profiles/default/viewlets.xml
heddex/tranquility/skins/heddex_tranquility_custom_images/actions-bullet.gif
heddex/tranquility/skins/heddex_tranquility_custom_images/actions-bullet.gif.metadata
heddex/tranquility/skins/heddex_tranquility_custom_images/body-bg.png
heddex/tranquility/skins/heddex_tranquility_custom_images/body-bg.png.metadata
heddex/tranquility/skins/heddex_tranquility_custom_images/bullet.gif
heddex/tranquility/skins/heddex_tranquility_custom_images/bullet.gif.metadata
heddex/tranquility/skins/heddex_tranquility_custom_images/favicon.ico
heddex/tranquility/skins/heddex_tranquility_custom_images/globalnav-bg.png
