Metadata-Version: 1.0
Name: heddex.tranquility
Version: 1.1
Summary: An installable theme for Plone 3.0
Home-page: http://svn.plone.org/svn/collective/
Author: Michael Krishtopa
Author-email: theo.ukr@gmail.com
License: GPL
Keywords: web zope plone theme
Platform: UNKNOWN
Classifier: Framework :: Plone
Classifier: Programming Language :: Python
Classifier: Topic :: Software Development :: Libraries :: Python Modules
